toggle_cbreak/__init__.py
toggle_cbreak-0.0.3.dist-info/METADATA
toggle_cbreak-0.0.3.dist-info/WHEEL
toggle_cbreak-0.0.3.dist-info/licenses/LICENSE
toggle_cbreak-0.0.3.dist-info/RECORD
