Metadata-Version: 2.3
Name: toggle_cbreak
Version: 0.0.3
Summary: toggles cbreak mode on terminal
Project-URL: Homepage, https://github.com/zlliu246/toggle_cbreak
Project-URL: Issues, https://github.com/zlliu246/toggle_cbreak/issues
Author-email: Liu Zuo Lin <zlliu246@gmail.com>
Classifier: License :: OSI Approved :: MIT License
Classifier: Operating System :: OS Independent
Classifier: Programming Language :: Python :: 3
Requires-Python: >=3.8
